{
  "generated_at": "2026-03-04T11:57:38Z",
  "started_at": "2026-03-04T11:55:25Z",
  "summary": {
    "vendors_checked": 84,
    "websites_live": 65,
    "websites_unreachable": 11,
    "acquisition_signals_detected": 5
  },
  "vendor_checks": [
    {
      "website_live": true,
      "http_status": 200,
      "checked_at": "2026-03-04T11:55:25Z",
      "funding_mentions": [
        "raise"
      ],
      "name": "Credo AI"
    },
    {
      "website_live": true,
      "http_status": 200,
      "checked_at": "2026-03-04T11:55:25Z",
      "funding_mentions": [
        "series a",
        "investment"
      ],
      "name": "Holistic AI"
    },
    {
      "website_live": true,
      "http_status": 200,
      "checked_at": "2026-03-04T11:55:26Z",
      "funding_mentions": [
        "raise"
      ],
      "name": "Fairly AI"
    },
    {
      "website_live": true,
      "http_status": 200,
      "checked_at": "2026-03-04T11:55:27Z",
      "name": "Monitaur"
    },
    {
      "website_live": true,
      "http_status": 200,
      "checked_at": "2026-03-04T11:55:28Z",
      "name": "2021.AI"
    },
    {
      "website_live": false,
      "http_status": -1,
      "checked_at": "2026-03-04T11:56:05Z",
      "name": "Saidot"
    },
    {
      "website_live": true,
      "http_status": 200,
      "checked_at": "2026-03-04T11:56:06Z",
      "name": "Trustible"
    },
    {
      "website_live": true,
      "http_status": 200,
      "checked_at": "2026-03-04T11:56:07Z",
      "funding_mentions": [
        "investment"
      ],
      "name": "ModelOp"
    },
    {
      "website_live": true,
      "http_status": 200,
      "checked_at": "2026-03-04T11:56:10Z",
      "funding_mentions": [
        "investment"
      ],
      "name": "Datatron"
    },
    {
      "website_live": true,
      "http_status": 200,
      "checked_at": "2026-03-04T11:56:11Z",
      "name": "Domino Data Lab"
    },
    {
      "website_live": true,
      "http_status": 200,
      "checked_at": "2026-03-04T11:56:12Z",
      "name": "ValidMind"
    },
    {
      "website_live": true,
      "http_status": 200,
      "checked_at": "2026-03-04T11:56:13Z",
      "funding_mentions": [
        "investment"
      ],
      "name": "Collibra"
    },
    {
      "website_live": true,
      "http_status": 200,
      "checked_at": "2026-03-04T11:56:13Z",
      "name": "OneTrust"
    },
    {
      "website_live": true,
      "http_status": 200,
      "checked_at": "2026-03-04T11:56:15Z",
      "name": "Dataiku"
    },
    {
      "website_live": true,
      "http_status": 200,
      "checked_at": "2026-03-04T11:56:15Z",
      "name": "Lakera AI"
    },
    {
      "name": "Prompt Security",
      "website": "https://www.prompt.security",
      "website_live": null,
      "checked_at": "2026-03-04T11:56:16Z",
      "skip_reason": "acquired"
    },
    {
      "website_live": true,
      "http_status": 200,
      "checked_at": "2026-03-04T11:56:16Z",
      "name": "Lasso Security"
    },
    {
      "name": "Robust Intelligence",
      "website": "https://www.cisco.com",
      "website_live": null,
      "checked_at": "2026-03-04T11:56:17Z",
      "skip_reason": "acquired"
    },
    {
      "website_live": true,
      "http_status": 200,
      "checked_at": "2026-03-04T11:56:17Z",
      "name": "Zenity"
    },
    {
      "website_live": true,
      "http_status": 200,
      "checked_at": "2026-03-04T11:56:18Z",
      "name": "Straiker"
    },
    {
      "name": "Aim Security",
      "website": "https://www.aim.security",
      "website_live": null,
      "checked_at": "2026-03-04T11:56:19Z",
      "skip_reason": "acquired"
    },
    {
      "website_live": true,
      "http_status": 200,
      "checked_at": "2026-03-04T11:56:19Z",
      "funding_mentions": [
        "raise",
        "investment"
      ],
      "name": "vijil"
    },
    {
      "website_live": false,
      "http_status": 404,
      "checked_at": "2026-03-04T11:56:20Z",
      "name": "Palo Alto Networks — Prisma AIRS"
    },
    {
      "website_live": true,
      "http_status": 200,
      "checked_at": "2026-03-04T11:56:20Z",
      "funding_mentions": [
        "series c",
        "raises"
      ],
      "name": "Fiddler AI"
    },
    {
      "website_live": true,
      "http_status": 200,
      "checked_at": "2026-03-04T11:56:21Z",
      "funding_mentions": [
        "investment"
      ],
      "name": "Arthur AI"
    },
    {
      "website_live": true,
      "http_status": 200,
      "checked_at": "2026-03-04T11:56:25Z",
      "name": "TruEra"
    },
    {
      "website_live": true,
      "http_status": 200,
      "checked_at": "2026-03-04T11:56:26Z",
      "name": "H2O.ai"
    },
    {
      "website_live": true,
      "http_status": 200,
      "checked_at": "2026-03-04T11:56:27Z",
      "name": "DataRobot"
    },
    {
      "website_live": true,
      "http_status": 200,
      "checked_at": "2026-03-04T11:56:28Z",
      "funding_mentions": [
        "raises"
      ],
      "name": "Mindgard"
    },
    {
      "website_live": true,
      "http_status": 200,
      "checked_at": "2026-03-04T11:56:28Z",
      "name": "HiddenLayer"
    },
    {
      "name": "CalypsoAI",
      "website": "https://www.f5.com",
      "website_live": null,
      "checked_at": "2026-03-04T11:56:29Z",
      "skip_reason": "acquired"
    },
    {
      "website_live": true,
      "http_status": 200,
      "checked_at": "2026-03-04T11:56:29Z",
      "name": "PointGuard AI"
    },
    {
      "name": "Protect AI",
      "website": "https://www.paloaltonetworks.com/prisma/airs",
      "website_live": null,
      "checked_at": "2026-03-04T11:56:30Z",
      "skip_reason": "acquired"
    },
    {
      "website_live": true,
      "http_status": 200,
      "checked_at": "2026-03-04T11:56:31Z",
      "name": "Arize AI"
    },
    {
      "name": "WhyLabs",
      "website": "https://www.whylabs.ai",
      "website_live": null,
      "checked_at": "2026-03-04T11:56:31Z",
      "skip_reason": "acquired"
    },
    {
      "website_live": true,
      "http_status": 200,
      "checked_at": "2026-03-04T11:56:31Z",
      "name": "Evidently AI"
    },
    {
      "name": "Aporia",
      "website": "https://www.aporia.com",
      "website_live": null,
      "checked_at": "2026-03-04T11:56:32Z",
      "skip_reason": "acquired"
    },
    {
      "website_live": true,
      "http_status": 200,
      "checked_at": "2026-03-04T11:56:32Z",
      "name": "Mona Labs"
    },
    {
      "website_live": true,
      "http_status": 200,
      "checked_at": "2026-03-04T11:56:33Z",
      "acquisition_signals": [
        "acquisition"
      ],
      "funding_mentions": [
        "$12 million",
        "funding"
      ],
      "name": "LatticeFlow AI"
    },
    {
      "name": "Securiti AI",
      "website": "https://securiti.ai",
      "website_live": null,
      "checked_at": "2026-03-04T11:56:33Z",
      "skip_reason": "acquired"
    },
    {
      "website_live": true,
      "http_status": 200,
      "checked_at": "2026-03-04T11:56:33Z",
      "name": "Nightfall AI"
    },
    {
      "website_live": true,
      "http_status": 200,
      "checked_at": "2026-03-04T11:56:34Z",
      "name": "BigID"
    },
    {
      "website_live": true,
      "http_status": 200,
      "checked_at": "2026-03-04T11:56:35Z",
      "name": "Proofpoint"
    },
    {
      "website_live": true,
      "http_status": 200,
      "checked_at": "2026-03-04T11:56:37Z",
      "funding_mentions": [
        "funding"
      ],
      "name": "Concentric AI"
    },
    {
      "website_live": true,
      "http_status": 200,
      "checked_at": "2026-03-04T11:56:40Z",
      "funding_mentions": [
        "series a"
      ],
      "name": "Azure AI Content Safety (Microsoft)"
    },
    {
      "website_live": false,
      "http_status": 404,
      "checked_at": "2026-03-04T11:56:41Z",
      "name": "Google Perspective API / Vertex AI Safety"
    },
    {
      "website_live": true,
      "http_status": 200,
      "checked_at": "2026-03-04T11:56:42Z",
      "funding_mentions": [
        "funding",
        "investment"
      ],
      "name": "AWS AI Content Moderation"
    },
    {
      "website_live": true,
      "http_status": 200,
      "checked_at": "2026-03-04T11:56:43Z",
      "acquisition_signals": [
        "acquisition"
      ],
      "funding_mentions": [
        "series a"
      ],
      "name": "Cloudflare AI Prompt Protection"
    },
    {
      "website_live": true,
      "http_status": 200,
      "checked_at": "2026-03-04T11:56:44Z",
      "funding_mentions": [
        "funding",
        "series a",
        "investment"
      ],
      "name": "Portal26"
    },
    {
      "website_live": true,
      "http_status": 200,
      "checked_at": "2026-03-04T11:56:45Z",
      "name": "AllTrue.ai TRiSM Hub"
    },
    {
      "website_live": true,
      "http_status": 200,
      "checked_at": "2026-03-04T11:56:46Z",
      "name": "Knostic"
    },
    {
      "website_live": true,
      "http_status": 200,
      "checked_at": "2026-03-04T11:56:47Z",
      "name": "Regulativ.ai"
    },
    {
      "website_live": true,
      "http_status": 200,
      "checked_at": "2026-03-04T11:56:47Z",
      "funding_mentions": [
        "investment"
      ],
      "name": "IBM — watsonx.governance"
    },
    {
      "website_live": false,
      "http_status": 404,
      "checked_at": "2026-03-04T11:56:49Z",
      "name": "Microsoft — Azure AI Safety & Governance Suite"
    },
    {
      "website_live": true,
      "http_status": 200,
      "checked_at": "2026-03-04T11:56:49Z",
      "funding_mentions": [
        "funding",
        "investment"
      ],
      "name": "AWS — AI Governance & Safety Portfolio"
    },
    {
      "website_live": false,
      "http_status": 404,
      "checked_at": "2026-03-04T11:56:51Z",
      "name": "Google — AI Safety & Governance"
    },
    {
      "website_live": true,
      "http_status": 200,
      "checked_at": "2026-03-04T11:56:51Z",
      "name": "Patronus AI"
    },
    {
      "website_live": false,
      "http_status": -1,
      "checked_at": "2026-03-04T11:56:58Z",
      "name": "TrojAI"
    },
    {
      "website_live": true,
      "http_status": 200,
      "checked_at": "2026-03-04T11:56:59Z",
      "acquisition_signals": [
        "acquired",
        "integrated into"
      ],
      "name": "Neptune.ai"
    },
    {
      "website_live": true,
      "http_status": 200,
      "checked_at": "2026-03-04T11:56:59Z",
      "acquisition_signals": [
        "now part of"
      ],
      "funding_mentions": [
        "funding",
        "investment"
      ],
      "name": "Armilla AI"
    },
    {
      "website_live": true,
      "http_status": 200,
      "checked_at": "2026-03-04T11:57:00Z",
      "acquisition_signals": [
        "acquisition"
      ],
      "funding_mentions": [
        "$16.4 billion",
        "$5 million",
        "raises",
        "raise",
        "investment"
      ],
      "name": "EQTY Lab"
    },
    {
      "website_live": true,
      "http_status": 200,
      "checked_at": "2026-03-04T11:57:01Z",
      "name": "Vals AI"
    },
    {
      "website_live": true,
      "http_status": 200,
      "checked_at": "2026-03-04T11:57:02Z",
      "funding_mentions": [
        "investment"
      ],
      "name": "Mind Foundry"
    },
    {
      "website_live": true,
      "http_status": 200,
      "checked_at": "2026-03-04T11:57:02Z",
      "name": "Howso"
    },
    {
      "website_live": false,
      "http_status": -1,
      "checked_at": "2026-03-04T11:57:09Z",
      "name": "Untangle AI"
    },
    {
      "website_live": true,
      "http_status": 200,
      "checked_at": "2026-03-04T11:57:10Z",
      "name": "CausaLens"
    },
    {
      "website_live": false,
      "http_status": -1,
      "checked_at": "2026-03-04T11:57:17Z",
      "name": "Censius"
    },
    {
      "website_live": true,
      "http_status": 200,
      "checked_at": "2026-03-04T11:57:18Z",
      "name": "Fairnow"
    },
    {
      "website_live": true,
      "http_status": 200,
      "checked_at": "2026-03-04T11:57:19Z",
      "name": "Anch.AI"
    },
    {
      "website_live": true,
      "http_status": 200,
      "checked_at": "2026-03-04T11:57:20Z",
      "funding_mentions": [
        "raises",
        "funding",
        "$3 billion"
      ],
      "name": "Atlan"
    },
    {
      "website_live": true,
      "http_status": 200,
      "checked_at": "2026-03-04T11:57:21Z",
      "funding_mentions": [
        "$11 million",
        "investment"
      ],
      "name": "RecordPoint"
    },
    {
      "website_live": true,
      "http_status": 200,
      "checked_at": "2026-03-04T11:57:21Z",
      "name": "Resistant AI"
    },
    {
      "website_live": false,
      "http_status": -1,
      "checked_at": "2026-03-04T11:57:29Z",
      "name": "SparkCognition"
    },
    {
      "website_live": true,
      "http_status": 200,
      "checked_at": "2026-03-04T11:57:29Z",
      "name": "SAS Institute"
    },
    {
      "website_live": true,
      "http_status": 200,
      "checked_at": "2026-03-04T11:57:30Z",
      "name": "FICO"
    },
    {
      "website_live": true,
      "http_status": 200,
      "checked_at": "2026-03-04T11:57:31Z",
      "name": "Salesforce"
    },
    {
      "website_live": true,
      "http_status": 200,
      "checked_at": "2026-03-04T11:57:31Z",
      "funding_mentions": [
        "investment"
      ],
      "name": "SAP"
    },
    {
      "website_live": false,
      "http_status": 403,
      "checked_at": "2026-03-04T11:57:32Z",
      "name": "ServiceNow"
    },
    {
      "website_live": true,
      "http_status": 200,
      "checked_at": "2026-03-04T11:57:33Z",
      "funding_mentions": [
        "investment"
      ],
      "name": "Rapid7"
    },
    {
      "website_live": true,
      "http_status": 200,
      "checked_at": "2026-03-04T11:57:34Z",
      "name": "LogicManager"
    },
    {
      "website_live": true,
      "http_status": 200,
      "checked_at": "2026-03-04T11:57:35Z",
      "funding_mentions": [
        "$135 million",
        "investment"
      ],
      "name": "RSA Security"
    },
    {
      "website_live": true,
      "http_status": 200,
      "checked_at": "2026-03-04T11:57:36Z",
      "funding_mentions": [
        "raise",
        "$969 billion",
        "investment"
      ],
      "name": "Moody's Analytics"
    },
    {
      "website_live": false,
      "http_status": 403,
      "checked_at": "2026-03-04T11:57:36Z",
      "name": "Akamai AI Firewall"
    },
    {
      "website_live": true,
      "http_status": 200,
      "checked_at": "2026-03-04T11:57:37Z",
      "name": "Qlik"
    }
  ],
  "regulatory_checks": [
    {
      "id": "eu-ai-act",
      "url": "https://artificialintelligenceact.eu/",
      "reachable": true,
      "checked_at": "2026-03-04T11:57:38Z",
      "found_terms": [
        "enforcement",
        "compliance",
        "deadline",
        "august 2026"
      ]
    },
    {
      "id": "nist-ai-rmf",
      "url": "https://www.nist.gov/artificial-intelligence",
      "reachable": true,
      "checked_at": "2026-03-04T11:57:38Z",
      "found_terms": [
        "ai rmf",
        "framework",
        "update"
      ]
    },
    {
      "id": "iso-42001",
      "url": "https://www.iso.org/standard/81230.html",
      "reachable": true,
      "checked_at": "2026-03-04T11:57:38Z",
      "found_terms": [
        "42001",
        "2024"
      ]
    }
  ]
}